liteflow.core-0.3.1-py3.6-nspkg.pth
liteflow/core/__init__.py
liteflow/core/configure.py
liteflow/core/abstractions/__init__.py
liteflow/core/abstractions/background_service.py
liteflow/core/abstractions/execution_pointer_factory.py
liteflow/core/abstractions/execution_result_processor.py
liteflow/core/abstractions/lock_provider.py
liteflow/core/abstractions/persistence_provider.py
liteflow/core/abstractions/queue_provider.py
liteflow/core/abstractions/workflow_executor.py
liteflow/core/abstractions/workflow_host.py
liteflow/core/abstractions/workflow_registry.py
liteflow/core/builders/__init__.py
liteflow/core/builders/step_builder.py
liteflow/core/builders/workflow_builder.py
liteflow/core/models/__init__.py
liteflow/core/models/event.py
liteflow/core/models/event_subscription.py
liteflow/core/models/execution_error.py
liteflow/core/models/execution_pointer.py
liteflow/core/models/execution_result.py
liteflow/core/models/step_body.py
liteflow/core/models/step_outcome.py
liteflow/core/models/workflow.py
liteflow/core/models/workflow_definition.py
liteflow/core/models/workflow_executor_result.py
liteflow/core/models/workflow_instance.py
liteflow/core/models/workflow_step.py
liteflow/core/primitives/__init__.py
liteflow/core/primitives/container_step_body.py
liteflow/core/primitives/delay.py
liteflow/core/primitives/foreach.py
liteflow/core/primitives/if_step.py
liteflow/core/primitives/schedule.py
liteflow/core/primitives/sequence.py
liteflow/core/primitives/wait_for.py
liteflow/core/primitives/while_step.py
liteflow/core/services/__init__.py
liteflow/core/services/event_consumer.py
liteflow/core/services/execution_pointer_factory.py
liteflow/core/services/execution_result_processor.py
liteflow/core/services/local_lock_provider.py
liteflow/core/services/local_queue_provider.py
liteflow/core/services/memory_persistence_provider.py
liteflow/core/services/queue_consumer.py
liteflow/core/services/runnable_poller.py
liteflow.core-0.3.1.dist-info/METADATA
liteflow.core-0.3.1.dist-info/RECORD
liteflow.core-0.3.1.dist-info/WHEEL
liteflow.core-0.3.1.dist-info/namespace_packages.txt
liteflow.core-0.3.1.dist-info/top_level.txt
