Metadata-Version: 2.1
Name: liteflow.core
Version: 0.3.1
Summary: Workflow library with pluggable persistence and scale out support
Home-page: https://github.com/danielgerlag/liteflow
Author: Daniel Gerlag
Author-email: daniel@gerlag.ca
License: MIT
Keywords: workflow
Platform: UNKNOWN
Classifier: Programming Language :: Python :: 3.6
Classifier: License :: OSI Approved :: MIT License
Classifier: Operating System :: OS Independent
Requires-Python: >=3.6
Requires-Dist: python-interface (>=1.4.0)
